xyz_points/__init__.py
xyz_points/admin.py
xyz_points/apis.py
xyz_points/apps.py
xyz_points/helper.py
xyz_points/models.py
xyz_points/receivers.py
xyz_points/serializers.py
xyz_points/signals.py
xyz_points/stores.py
xyz_points/migrations/0001_initial.py
xyz_points/migrations/__init__.py
xyz_points-0.2.2.dist-info/METADATA
xyz_points-0.2.2.dist-info/WHEEL
xyz_points-0.2.2.dist-info/top_level.txt
xyz_points-0.2.2.dist-info/RECORD
